script_bisect/__init__.py
script_bisect/__main__.py
script_bisect/auto_dependency_fixer.py
script_bisect/bisection_orchestrator.py
script_bisect/bisector.py
script_bisect/cache_cli.py
script_bisect/cache_system.py
script_bisect/cli.py
script_bisect/cli_display.py
script_bisect/correction_patterns.py
script_bisect/dependency_detector.py
script_bisect/dependency_mappings.py
script_bisect/editor_integration.py
script_bisect/end_state_menu.py
script_bisect/exceptions.py
script_bisect/interactive.py
script_bisect/issue_importer.py
script_bisect/parser.py
script_bisect/repository_manager.py
script_bisect/repository_mappings.py
script_bisect/runner.py
script_bisect/script_autocorrect.py
script_bisect/script_generator.py
script_bisect/utils.py
script_bisect/validation.py
script_bisect-0.1.2.dist-info/METADATA
script_bisect-0.1.2.dist-info/WHEEL
script_bisect-0.1.2.dist-info/entry_points.txt
script_bisect-0.1.2.dist-info/RECORD
