Metadata-Version: 2.4
Name: script-bisect
Version: 0.1.2
Summary: Bisect package versions in PEP 723 Python scripts using git bisect and uv
Project-URL: Documentation, https://github.com/ianhi/script-bisect#readme
Project-URL: Issues, https://github.com/ianhi/script-bisect/issues
Project-URL: Source, https://github.com/ianhi/script-bisect
Author: uv-bisect contributors
License-Expression: MIT
Keywords: bisect,debugging,dependencies,git,pep723,python,uv
Classifier: Development Status :: 4 - Beta
Classifier: Environment :: Console
Classifier: Intended Audience :: Developers
Classifier: License :: OSI Approved :: MIT License
Classifier: Operating System :: OS Independent
Classifier: Programming Language :: Python
Classifier: Programming Language :: Python :: 3.12
Classifier: Programming Language :: Python :: 3.13
Classifier: Topic :: Software Development
Classifier: Topic :: Software Development :: Version Control :: Git
Requires-Python: >=3.12
Requires-Dist: click>=8.0
Requires-Dist: gitpython>=3.1
Requires-Dist: mistune>=3.1.4
Requires-Dist: packaging>=23.0
Requires-Dist: prompt-toolkit>=3.0.52
Requires-Dist: requests>=2.32.5
Requires-Dist: rich>=13.0
Requires-Dist: tomli-w>=1.0
Provides-Extra: dev
Requires-Dist: mypy>=1.0; extra == 'dev'
Requires-Dist: pre-commit>=3.0; extra == 'dev'
Requires-Dist: pytest-cov>=4.0; extra == 'dev'
Requires-Dist: pytest-mock>=3.10; extra == 'dev'
Requires-Dist: pytest>=7.0; extra == 'dev'
Requires-Dist: ruff>=0.1.0; extra == 'dev'
Requires-Dist: types-requests>=2.0; extra == 'dev'
